<dqm4hepHotPixelsMap>
<sensor id="1">
<pixel x="10"  y="393"/>
<pixel x="38"  y="397"/>
<pixel x="39"  y="63"/>
<pixel x="42"  y="178"/>
<pixel x="44"  y="136"/>
<pixel x="44"  y="436"/>
<pixel x="48"  y="377"/>
<pixel x="51"  y="516"/>
<pixel x="52"  y="294"/>
<pixel x="59"  y="41"/>
<pixel x="61"  y="20"/>
<pixel x="81"  y="410"/>
<pixel x="118"  y="6"/>
<pixel x="125"  y="431"/>
<pixel x="131"  y="72"/>
<pixel x="132"  y="35"/>
<pixel x="134"  y="341"/>
<pixel x="158"  y="232"/>
<pixel x="163"  y="309"/>
<pixel x="169"  y="42"/>
<pixel x="173"  y="283"/>
<pixel x="189"  y="289"/>
<pixel x="205"  y="527"/>
<pixel x="216"  y="522"/>
<pixel x="222"  y="180"/>
<pixel x="242"  y="47"/>
<pixel x="253"  y="114"/>
<pixel x="268"  y="142"/>
<pixel x="270"  y="19"/>
<pixel x="272"  y="40"/>
<pixel x="276"  y="397"/>
<pixel x="298"  y="564"/>
<pixel x="373"  y="205"/>
<pixel x="403"  y="19"/>
<pixel x="426"  y="38"/>
<pixel x="450"  y="564"/>
<pixel x="457"  y="451"/>
<pixel x="485"  y="337"/>
<pixel x="514"  y="109"/>
<pixel x="541"  y="90"/>
<pixel x="546"  y="274"/>
<pixel x="550"  y="480"/>
<pixel x="578"  y="124"/>
<pixel x="591"  y="413"/>
<pixel x="636"  y="433"/>
<pixel x="687"  y="114"/>
<pixel x="769"  y="59"/>
<pixel x="798"  y="257"/>
<pixel x="806"  y="87"/>
<pixel x="824"  y="437"/>
<pixel x="835"  y="164"/>
<pixel x="920"  y="518"/>
<pixel x="924"  y="107"/>
<pixel x="933"  y="472"/>
<pixel x="945"  y="416"/>
<pixel x="950"  y="212"/>
<pixel x="966"  y="146"/>
<pixel x="983"  y="497"/>
<pixel x="994"  y="501"/>
<pixel x="995"  y="430"/>
<pixel x="1002"  y="261"/>
<pixel x="1015"  y="565"/>
<pixel x="1015"  y="567"/>
<pixel x="1022"  y="557"/>
<pixel x="1044"  y="484"/>
<pixel x="1053"  y="177"/>
<pixel x="1064"  y="453"/>
<pixel x="1074"  y="233"/>
<pixel x="1087"  y="326"/>
<pixel x="1089"  y="211"/>
<pixel x="1110"  y="142"/>
<pixel x="1126"  y="142"/>
<pixel x="1132"  y="565"/>
<pixel x="1141"  y="371"/>
<pixel x="1147"  y="407"/>
</sensor>
<sensor id="2">
<pixel x="20"  y="82"/>
<pixel x="29"  y="275"/>
<pixel x="62"  y="328"/>
<pixel x="66"  y="164"/>
<pixel x="67"  y="251"/>
<pixel x="119"  y="182"/>
<pixel x="134"  y="185"/>
<pixel x="189"  y="381"/>
<pixel x="203"  y="101"/>
<pixel x="236"  y="143"/>
<pixel x="307"  y="218"/>
<pixel x="353"  y="71"/>
<pixel x="363"  y="446"/>
<pixel x="394"  y="91"/>
<pixel x="449"  y="28"/>
<pixel x="470"  y="5"/>
<pixel x="483"  y="185"/>
<pixel x="486"  y="329"/>
<pixel x="499"  y="373"/>
<pixel x="504"  y="179"/>
<pixel x="565"  y="96"/>
<pixel x="567"  y="207"/>
<pixel x="570"  y="234"/>
<pixel x="584"  y="424"/>
<pixel x="611"  y="96"/>
<pixel x="654"  y="158"/>
<pixel x="663"  y="303"/>
<pixel x="703"  y="378"/>
<pixel x="716"  y="81"/>
<pixel x="716"  y="454"/>
<pixel x="725"  y="272"/>
<pixel x="752"  y="174"/>
<pixel x="764"  y="131"/>
<pixel x="770"  y="111"/>
<pixel x="775"  y="23"/>
<pixel x="783"  y="30"/>
<pixel x="802"  y="147"/>
<pixel x="846"  y="245"/>
<pixel x="866"  y="81"/>
<pixel x="866"  y="437"/>
<pixel x="893"  y="469"/>
<pixel x="903"  y="148"/>
<pixel x="907"  y="74"/>
<pixel x="908"  y="442"/>
<pixel x="974"  y="463"/>
<pixel x="985"  y="327"/>
<pixel x="1008"  y="29"/>
<pixel x="1015"  y="369"/>
<pixel x="1028"  y="280"/>
<pixel x="1028"  y="306"/>
<pixel x="1047"  y="318"/>
<pixel x="1048"  y="155"/>
<pixel x="1049"  y="455"/>
<pixel x="1052"  y="238"/>
<pixel x="1065"  y="390"/>
<pixel x="1066"  y="352"/>
<pixel x="1100"  y="457"/>
<pixel x="1104"  y="172"/>
<pixel x="1122"  y="358"/>
<pixel x="1123"  y="33"/>
<pixel x="1127"  y="195"/>
<pixel x="1129"  y="107"/>
<pixel x="1133"  y="4"/>
<pixel x="1149"  y="419"/>
</sensor>
<sensor id="3">
<pixel x="8"  y="157"/>
<pixel x="24"  y="156"/>
<pixel x="73"  y="100"/>
<pixel x="118"  y="146"/>
<pixel x="118"  y="360"/>
<pixel x="143"  y="134"/>
<pixel x="204"  y="565"/>
<pixel x="226"  y="341"/>
<pixel x="325"  y="525"/>
<pixel x="331"  y="12"/>
<pixel x="332"  y="390"/>
<pixel x="336"  y="21"/>
<pixel x="402"  y="99"/>
<pixel x="442"  y="128"/>
<pixel x="455"  y="276"/>
<pixel x="467"  y="131"/>
<pixel x="471"  y="473"/>
<pixel x="476"  y="411"/>
<pixel x="487"  y="294"/>
<pixel x="488"  y="355"/>
<pixel x="489"  y="573"/>
<pixel x="496"  y="17"/>
<pixel x="530"  y="341"/>
<pixel x="536"  y="27"/>
<pixel x="543"  y="288"/>
<pixel x="567"  y="408"/>
<pixel x="571"  y="18"/>
<pixel x="600"  y="88"/>
<pixel x="619"  y="323"/>
<pixel x="636"  y="94"/>
<pixel x="638"  y="114"/>
<pixel x="646"  y="426"/>
<pixel x="654"  y="11"/>
<pixel x="662"  y="457"/>
<pixel x="676"  y="109"/>
<pixel x="680"  y="13"/>
<pixel x="695"  y="167"/>
<pixel x="697"  y="171"/>
<pixel x="715"  y="269"/>
<pixel x="730"  y="116"/>
<pixel x="734"  y="489"/>
<pixel x="742"  y="350"/>
<pixel x="747"  y="233"/>
<pixel x="749"  y="18"/>
<pixel x="756"  y="341"/>
<pixel x="757"  y="6"/>
<pixel x="770"  y="36"/>
<pixel x="774"  y="146"/>
<pixel x="775"  y="214"/>
<pixel x="780"  y="273"/>
<pixel x="793"  y="410"/>
<pixel x="797"  y="288"/>
<pixel x="814"  y="384"/>
<pixel x="827"  y="42"/>
<pixel x="829"  y="125"/>
<pixel x="837"  y="440"/>
<pixel x="845"  y="502"/>
<pixel x="852"  y="421"/>
<pixel x="869"  y="481"/>
<pixel x="877"  y="461"/>
<pixel x="890"  y="323"/>
<pixel x="892"  y="411"/>
<pixel x="910"  y="133"/>
<pixel x="921"  y="288"/>
<pixel x="924"  y="569"/>
<pixel x="934"  y="355"/>
<pixel x="937"  y="439"/>
<pixel x="938"  y="147"/>
<pixel x="946"  y="386"/>
<pixel x="951"  y="564"/>
<pixel x="956"  y="136"/>
<pixel x="956"  y="324"/>
<pixel x="957"  y="390"/>
<pixel x="967"  y="523"/>
<pixel x="974"  y="377"/>
<pixel x="982"  y="227"/>
<pixel x="1000"  y="158"/>
<pixel x="1008"  y="90"/>
<pixel x="1023"  y="28"/>
<pixel x="1034"  y="54"/>
<pixel x="1038"  y="72"/>
<pixel x="1043"  y="348"/>
<pixel x="1047"  y="316"/>
<pixel x="1048"  y="201"/>
<pixel x="1048"  y="475"/>
<pixel x="1053"  y="159"/>
<pixel x="1068"  y="156"/>
<pixel x="1074"  y="378"/>
<pixel x="1084"  y="359"/>
<pixel x="1087"  y="270"/>
<pixel x="1089"  y="129"/>
<pixel x="1091"  y="509"/>
<pixel x="1104"  y="453"/>
<pixel x="1108"  y="136"/>
<pixel x="1109"  y="278"/>
<pixel x="1115"  y="79"/>
<pixel x="1128"  y="47"/>
<pixel x="1129"  y="168"/>
<pixel x="1131"  y="124"/>
<pixel x="1142"  y="195"/>
<pixel x="1149"  y="328"/>
<pixel x="1149"  y="384"/>
</sensor>
<sensor id="4">
<pixel x="8"  y="139"/>
<pixel x="12"  y="135"/>
<pixel x="19"  y="27"/>
<pixel x="20"  y="120"/>
<pixel x="34"  y="55"/>
<pixel x="39"  y="45"/>
<pixel x="39"  y="551"/>
<pixel x="40"  y="430"/>
<pixel x="44"  y="366"/>
<pixel x="56"  y="114"/>
<pixel x="96"  y="481"/>
<pixel x="98"  y="529"/>
<pixel x="100"  y="211"/>
<pixel x="114"  y="319"/>
<pixel x="120"  y="114"/>
<pixel x="120"  y="318"/>
<pixel x="121"  y="332"/>
<pixel x="171"  y="180"/>
<pixel x="190"  y="408"/>
<pixel x="207"  y="347"/>
<pixel x="229"  y="13"/>
<pixel x="246"  y="35"/>
<pixel x="326"  y="282"/>
<pixel x="327"  y="16"/>
<pixel x="331"  y="64"/>
<pixel x="343"  y="3"/>
<pixel x="358"  y="331"/>
<pixel x="362"  y="141"/>
<pixel x="364"  y="153"/>
<pixel x="378"  y="411"/>
<pixel x="385"  y="104"/>
<pixel x="386"  y="462"/>
<pixel x="402"  y="51"/>
<pixel x="410"  y="45"/>
<pixel x="414"  y="400"/>
<pixel x="419"  y="300"/>
<pixel x="445"  y="114"/>
<pixel x="448"  y="336"/>
<pixel x="451"  y="573"/>
<pixel x="452"  y="459"/>
<pixel x="452"  y="551"/>
<pixel x="481"  y="115"/>
<pixel x="481"  y="483"/>
<pixel x="502"  y="374"/>
<pixel x="537"  y="54"/>
<pixel x="546"  y="217"/>
<pixel x="566"  y="39"/>
<pixel x="576"  y="530"/>
<pixel x="584"  y="286"/>
<pixel x="594"  y="115"/>
<pixel x="654"  y="569"/>
<pixel x="659"  y="73"/>
<pixel x="684"  y="107"/>
<pixel x="685"  y="83"/>
<pixel x="740"  y="384"/>
<pixel x="756"  y="418"/>
<pixel x="761"  y="340"/>
<pixel x="812"  y="364"/>
<pixel x="841"  y="0"/>
<pixel x="841"  y="56"/>
<pixel x="851"  y="214"/>
<pixel x="912"  y="142"/>
<pixel x="949"  y="45"/>
<pixel x="952"  y="421"/>
<pixel x="1025"  y="164"/>
<pixel x="1030"  y="152"/>
<pixel x="1039"  y="79"/>
<pixel x="1060"  y="290"/>
<pixel x="1081"  y="6"/>
</sensor>
<sensor id="5">
<pixel x="5"  y="27"/>
<pixel x="12"  y="210"/>
<pixel x="30"  y="505"/>
<pixel x="61"  y="505"/>
<pixel x="74"  y="23"/>
<pixel x="76"  y="400"/>
<pixel x="78"  y="159"/>
<pixel x="93"  y="6"/>
<pixel x="122"  y="359"/>
<pixel x="123"  y="95"/>
<pixel x="128"  y="368"/>
<pixel x="135"  y="488"/>
<pixel x="190"  y="265"/>
<pixel x="199"  y="152"/>
<pixel x="203"  y="67"/>
<pixel x="204"  y="262"/>
<pixel x="222"  y="46"/>
<pixel x="231"  y="61"/>
<pixel x="261"  y="86"/>
<pixel x="263"  y="366"/>
<pixel x="268"  y="38"/>
<pixel x="299"  y="80"/>
<pixel x="316"  y="414"/>
<pixel x="317"  y="346"/>
<pixel x="340"  y="500"/>
<pixel x="363"  y="6"/>
<pixel x="365"  y="494"/>
<pixel x="385"  y="69"/>
<pixel x="386"  y="12"/>
<pixel x="395"  y="89"/>
<pixel x="398"  y="72"/>
<pixel x="402"  y="115"/>
<pixel x="404"  y="423"/>
<pixel x="418"  y="282"/>
<pixel x="418"  y="470"/>
<pixel x="419"  y="318"/>
<pixel x="422"  y="387"/>
<pixel x="431"  y="254"/>
<pixel x="458"  y="570"/>
<pixel x="473"  y="82"/>
<pixel x="479"  y="397"/>
<pixel x="480"  y="243"/>
<pixel x="493"  y="29"/>
<pixel x="503"  y="169"/>
<pixel x="505"  y="233"/>
<pixel x="510"  y="232"/>
<pixel x="525"  y="318"/>
<pixel x="533"  y="9"/>
<pixel x="536"  y="537"/>
<pixel x="543"  y="363"/>
<pixel x="545"  y="164"/>
<pixel x="562"  y="293"/>
<pixel x="566"  y="165"/>
<pixel x="608"  y="10"/>
<pixel x="642"  y="425"/>
<pixel x="657"  y="240"/>
<pixel x="657"  y="359"/>
<pixel x="662"  y="0"/>
<pixel x="673"  y="260"/>
<pixel x="685"  y="408"/>
<pixel x="695"  y="375"/>
<pixel x="696"  y="17"/>
<pixel x="714"  y="550"/>
<pixel x="719"  y="292"/>
<pixel x="721"  y="122"/>
<pixel x="726"  y="265"/>
<pixel x="736"  y="133"/>
<pixel x="747"  y="561"/>
<pixel x="755"  y="251"/>
<pixel x="791"  y="207"/>
<pixel x="802"  y="397"/>
<pixel x="819"  y="477"/>
<pixel x="829"  y="125"/>
<pixel x="839"  y="439"/>
<pixel x="843"  y="386"/>
<pixel x="857"  y="370"/>
<pixel x="861"  y="105"/>
<pixel x="862"  y="29"/>
<pixel x="866"  y="171"/>
<pixel x="866"  y="179"/>
<pixel x="878"  y="293"/>
<pixel x="886"  y="114"/>
<pixel x="889"  y="340"/>
<pixel x="892"  y="321"/>
<pixel x="898"  y="434"/>
<pixel x="911"  y="132"/>
<pixel x="916"  y="35"/>
<pixel x="916"  y="184"/>
<pixel x="929"  y="463"/>
<pixel x="932"  y="522"/>
<pixel x="933"  y="463"/>
<pixel x="935"  y="211"/>
<pixel x="937"  y="366"/>
<pixel x="938"  y="243"/>
<pixel x="940"  y="210"/>
<pixel x="954"  y="92"/>
<pixel x="954"  y="564"/>
<pixel x="972"  y="528"/>
<pixel x="976"  y="406"/>
<pixel x="978"  y="468"/>
<pixel x="980"  y="459"/>
<pixel x="985"  y="539"/>
<pixel x="988"  y="322"/>
<pixel x="992"  y="277"/>
<pixel x="995"  y="500"/>
<pixel x="996"  y="114"/>
<pixel x="1014"  y="573"/>
<pixel x="1018"  y="195"/>
<pixel x="1020"  y="464"/>
<pixel x="1024"  y="327"/>
<pixel x="1024"  y="345"/>
<pixel x="1028"  y="22"/>
<pixel x="1029"  y="504"/>
<pixel x="1032"  y="263"/>
<pixel x="1040"  y="142"/>
<pixel x="1049"  y="249"/>
<pixel x="1068"  y="109"/>
<pixel x="1069"  y="500"/>
<pixel x="1069"  y="520"/>
<pixel x="1072"  y="65"/>
<pixel x="1079"  y="522"/>
<pixel x="1083"  y="148"/>
<pixel x="1085"  y="434"/>
<pixel x="1091"  y="331"/>
<pixel x="1098"  y="236"/>
<pixel x="1104"  y="148"/>
<pixel x="1111"  y="12"/>
<pixel x="1111"  y="100"/>
<pixel x="1111"  y="284"/>
<pixel x="1115"  y="139"/>
<pixel x="1115"  y="362"/>
<pixel x="1118"  y="337"/>
<pixel x="1128"  y="409"/>
<pixel x="1137"  y="395"/>
<pixel x="1143"  y="330"/>
<pixel x="1144"  y="541"/>
</sensor>
<sensor id="6">
<pixel x="48"  y="93"/>
<pixel x="57"  y="213"/>
<pixel x="190"  y="122"/>
<pixel x="202"  y="564"/>
<pixel x="344"  y="161"/>
<pixel x="357"  y="252"/>
<pixel x="382"  y="49"/>
<pixel x="453"  y="252"/>
<pixel x="462"  y="95"/>
<pixel x="462"  y="244"/>
<pixel x="475"  y="87"/>
<pixel x="527"  y="253"/>
<pixel x="622"  y="4"/>
<pixel x="624"  y="49"/>
<pixel x="631"  y="36"/>
<pixel x="757"  y="246"/>
<pixel x="824"  y="79"/>
<pixel x="835"  y="329"/>
<pixel x="882"  y="19"/>
<pixel x="906"  y="459"/>
<pixel x="950"  y="215"/>
<pixel x="951"  y="277"/>
<pixel x="953"  y="206"/>
<pixel x="954"  y="423"/>
<pixel x="978"  y="45"/>
<pixel x="986"  y="435"/>
<pixel x="993"  y="427"/>
<pixel x="1030"  y="456"/>
<pixel x="1036"  y="284"/>
<pixel x="1048"  y="399"/>
<pixel x="1059"  y="290"/>
<pixel x="1062"  y="402"/>
<pixel x="1078"  y="119"/>
<pixel x="1083"  y="148"/>
<pixel x="1123"  y="554"/>
<pixel x="1148"  y="378"/>
</sensor>
</dqm4hepHotPixelsMap>
